{
	"animations": [
		{
			"loop": false,
			"offsets": [
				0,
				0
			],
			"anim": "idle",
			"fps": 15,
			"name": "yuri idle",
			"indices": []
		},
		{
			"loop": false,
			"offsets": [
				0,
				0
			],
			"anim": "singLEFT",
			"fps": 15,
			"name": "yuri left",
			"indices": []
		},
		{
			"loop": false,
			"offsets": [
				0,
				0
			],
			"anim": "singDOWN",
			"fps": 15,
			"name": "yuri down",
			"indices": []
		},
		{
			"loop": false,
			"offsets": [
				0,
				0
			],
			"anim": "singUP",
			"fps": 15,
			"name": "yuri up",
			"indices": []
		},
		{
			"loop": false,
			"offsets": [
				0,
				0
			],
			"anim": "singRIGHT",
			"fps": 15,
			"name": "yuri right",
			"indices": []
		},
		{
			"loop": false,
			"offsets": [
				0,
				0
			],
			"anim": "deepbreaths",
			"fps": 12,
			"name": "yuri deepbreaths",
			"indices": []
		}
	],
	"no_antialiasing": false,
	"image": "characters/yuri",
	"position": [
		200,
		-120
	],
	"healthicon": "yursuki",
	"flip_x": false,
	"healthbar_colors": [
		158,
		114,
		210
	],
	"camera_position": [
		-240,
		-270
	],
	"sing_duration": 6.1,
	"scale": 1.1
}